mlops/__init__.py
mlops/monitoring.py
mlops/tracking.py
mlops/config/__init__.py
mlops/config/config.py
mlops/exceptions/__init__.py
mlops/exceptions/iteration.py
mlops/exceptions/mailgun.py
mlops/exceptions/monitoring.py
mlops/exceptions/tracking.py
mlops/src/__init__.py
mlops/src/chart.py
mlops/src/dataset.py
mlops/src/iteration.py
mlops/src/mailgun.py
mlops/src/monitored_model.py
mlops_ai-1.3.6.dist-info/METADATA
mlops_ai-1.3.6.dist-info/WHEEL
mlops_ai-1.3.6.dist-info/top_level.txt
mlops_ai-1.3.6.dist-info/RECORD
