Metadata-Version: 2.1
Name: mlops-ai
Version: 1.3.6
Summary: Mlops-ai library for managing machine learning projects, experiments, iterations and datasets.
Home-page: https://mlops-ai.github.io/mlops/
Author: Kacper Pękalski, Kajetan Szal, Jędrzej Rybczyński
Author-email: kac.pekalski1@gmail.com
License: Apache License 2.0
Project-URL: Documentation, https://mlops-ai.github.io/mlops/library_docs/library_overview.html
Project-URL: Repository, https://github.com/mlops-ai/mlops
Classifier: License :: OSI Approved :: Apache Software License
Classifier: Operating System :: OS Independent
Classifier: Programming Language :: Python :: 3.9
Classifier: Programming Language :: Python :: 3.10
Classifier: Programming Language :: Python :: 3.11
Requires-Dist: requests ==2.29.0
Requires-Dist: scikit-learn ==1.3.0
Requires-Dist: torch ==2.1.1
Requires-Dist: json2html ==1.3.0
